scrapy_zyte_smartproxy/__init__.py
scrapy_zyte_smartproxy/middleware.py
scrapy_zyte_smartproxy/utils.py
scrapy_zyte_smartproxy-2.4.1.dist-info/licenses/LICENSE.txt
scrapy_zyte_smartproxy-2.4.1.dist-info/METADATA
scrapy_zyte_smartproxy-2.4.1.dist-info/WHEEL
scrapy_zyte_smartproxy-2.4.1.dist-info/top_level.txt
scrapy_zyte_smartproxy-2.4.1.dist-info/RECORD
